hsproxy
