Metadata-Version: 2.1
Name: hsproxy
Version: 0.0.3
Summary: hsproxy
Home-page: https://github.com/iuser-dev/iuser_i18n/
Author: iuser
Author-email: iuser.link@gmail.com
License-File: LICENSE
